{"totalCoins":13,"z_length":36.0,"data":[{"name":"palm","pos":{"x":0.1899999976158142,"y":-0.3499999940395355,"z":10.300000190734864},"rot":{"x":0.0,"y":270.0,"z":0.0},"fullRotationData":[],"timelineAnimation":[],"bossSettings":[],"moveForward":[],"soData":[],"isChild":false},{"name":"Coin","pos":{"x":5.550000190734863,"y":1.559999942779541,"z":3.819999933242798},"rot":{"x":0.0,"y":0.0,"z":0.0},"fullRotationData":[],"timelineAnimation":[],"bossSettings":[],"moveForward":[],"soData":[],"isChild":false},{"name":"Coin","pos":{"x":-0.029999999329447748,"y":1.559999942779541,"z":-10.260000228881836},"rot":{"x":0.0,"y":0.0,"z":0.0},"fullRotationData":[],"timelineAnimation":[],"bossSettings":[],"moveForward":[],"soData":[],"isChild":false},{"name":"Coin","pos":{"x":3.950000047683716,"y":1.559999942779541,"z":1.3899999856948853},"rot":{"x":0.0,"y":0.0,"z":0.0},"fullRotationData":[],"timelineAnimation":[],"bossSettings":[],"moveForward":[],"soData":[],"isChild":false},{"name":"Coin","pos":{"x":0.0,"y":1.559999942779541,"z":-16.56999969482422},"rot":{"x":0.0,"y":0.0,"z":0.0},"fullRotationData":[],"timelineAnimation":[],"bossSettings":[],"moveForward":[],"soData":[],"isChild":false},{"name":"Coin","pos":{"x":-6.159999847412109,"y":1.559999942779541,"z":6.739999771118164},"rot":{"x":0.0,"y":0.0,"z":0.0},"fullRotationData":[],"timelineAnimation":[],"bossSettings":[],"moveForward":[],"soData":[],"isChild":false},{"name":"Coin","pos":{"x":1.3200000524520875,"y":1.559999942779541,"z":-1.0700000524520875},"rot":{"x":0.0,"y":0.0,"z":0.0},"fullRotationData":[],"timelineAnimation":[],"bossSettings":[],"moveForward":[],"soData":[],"isChild":false},{"name":"Coin","pos":{"x":-4.75,"y":1.559999942779541,"z":3.819999933242798},"rot":{"x":0.0,"y":0.0,"z":0.0},"fullRotationData":[],"timelineAnimation":[],"bossSettings":[],"moveForward":[],"soData":[],"isChild":false},{"name":"Coin","pos":{"x":-3.2100000381469728,"y":1.559999942779541,"z":1.2699999809265137},"rot":{"x":0.0,"y":0.0,"z":0.0},"fullRotationData":[],"timelineAnimation":[],"bossSettings":[],"moveForward":[],"soData":[],"isChild":false},{"name":"Coin","pos":{"x":0.03999999910593033,"y":1.559999942779541,"z":-7.199999809265137},"rot":{"x":0.0,"y":0.0,"z":0.0},"fullRotationData":[],"timelineAnimation":[],"bossSettings":[],"moveForward":[],"soData":[],"isChild":false},{"name":"Coin","pos":{"x":-0.05000000074505806,"y":1.559999942779541,"z":-4.510000228881836},"rot":{"x":0.0,"y":0.0,"z":0.0},"fullRotationData":[],"timelineAnimation":[],"bossSettings":[],"moveForward":[],"soData":[],"isChild":false},{"name":"Coin","pos":{"x":6.590000152587891,"y":1.559999942779541,"z":6.739999771118164},"rot":{"x":0.0,"y":0.0,"z":0.0},"fullRotationData":[],"timelineAnimation":[],"bossSettings":[],"moveForward":[],"soData":[],"isChild":false},{"name":"Coin","pos":{"x":-1.0499999523162842,"y":1.559999942779541,"z":-1.0700000524520875},"rot":{"x":0.0,"y":0.0,"z":0.0},"fullRotationData":[],"timelineAnimation":[],"bossSettings":[],"moveForward":[],"soData":[],"isChild":false},{"name":"Coin","pos":{"x":0.03999999910593033,"y":1.559999942779541,"z":-13.289999961853028},"rot":{"x":0.0,"y":0.0,"z":0.0},"fullRotationData":[],"timelineAnimation":[],"bossSettings":[],"moveForward":[],"soData":[],"isChild":false},{"name":"extralargeBlock1","pos":{"x":-5.989999771118164,"y":-1.25,"z":0.0},"rot":{"x":0.0,"y":0.0,"z":0.0},"fullRotationData":[],"timelineAnimation":[],"bossSettings":[],"moveForward":[],"soData":[],"isChild":false},{"name":"extralargeBlock1","pos":{"x":-5.989999771118164,"y":-1.25,"z":12.0},"rot":{"x":0.0,"y":0.0,"z":0.0},"fullRotationData":[],"timelineAnimation":[],"bossSettings":[],"moveForward":[],"soData":[],"isChild":false},{"name":"extralargeBlock1","pos":{"x":5.980000019073486,"y":-1.25,"z":0.0},"rot":{"x":0.0,"y":0.0,"z":0.0},"fullRotationData":[],"timelineAnimation":[],"bossSettings":[],"moveForward":[],"soData":[],"isChild":false},{"name":"extralargeBlock1","pos":{"x":-0.019999999552965165,"y":-1.25,"z":-12.0},"rot":{"x":0.0,"y":0.0,"z":0.0},"fullRotationData":[],"timelineAnimation":[],"bossSettings":[],"moveForward":[],"soData":[],"isChild":false},{"name":"extralargeBlock1","pos":{"x":5.980000019073486,"y":-1.25,"z":12.0},"rot":{"x":0.0,"y":0.0,"z":0.0},"fullRotationData":[],"timelineAnimation":[],"bossSettings":[],"moveForward":[],"soData":[],"isChild":false},{"name":"palm","pos":{"x":9.399999618530274,"y":-2.8499999046325685,"z":-3.880000114440918},"rot":{"x":0.0,"y":0.0,"z":0.0},"fullRotationData":[],"timelineAnimation":[],"bossSettings":[],"moveForward":[],"soData":[],"isChild":false},{"name":"palm","pos":{"x":-9.899999618530274,"y":-1.0499999523162842,"z":-4.199999809265137},"rot":{"x":0.0,"y":180.0,"z":0.0},"fullRotationData":[],"timelineAnimation":[],"bossSettings":[],"moveForward":[],"soData":[],"isChild":false},{"name":"enemyFrontal","pos":{"x":-6.400000095367432,"y":1.4600000381469727,"z":-1.2999999523162842},"rot":{"x":0.0,"y":180.0,"z":0.0},"fullRotationData":[],"timelineAnimation":[],"bossSettings":[],"moveForward":[{"speed":4.0,"randomSpeedDiff":0.0,"moveBackIn":0.0}],"soData":[{"size":{"x":0.0,"y":0.0,"z":0.0},"bumperForce":0.0,"random_pos_x":0.0,"minPayers":2}],"isChild":false},{"name":"enemyFrontal","pos":{"x":7.400000095367432,"y":1.4600000381469727,"z":-1.2999999523162842},"rot":{"x":0.0,"y":180.0,"z":0.0},"fullRotationData":[],"timelineAnimation":[],"bossSettings":[],"moveForward":[{"speed":4.0,"randomSpeedDiff":0.0,"moveBackIn":0.0}],"soData":[{"size":{"x":0.0,"y":0.0,"z":0.0},"bumperForce":0.0,"random_pos_x":0.0,"minPayers":2}],"isChild":false}]}