{"totalCoins":0,"z_length":60.0,"data":[{"name":"extralargeBlock1","pos":{"x":0.0,"y":-1.5,"z":-23.700000762939454},"rot":{"x":0.0,"y":45.000003814697269,"z":0.0},"fullRotationData":[],"timelineAnimation":[],"bossSettings":[],"moveForward":[],"soData":[],"isChild":false},{"name":"extralargeBlock1","pos":{"x":-9.199999809265137,"y":-1.5,"z":-23.700000762939454},"rot":{"x":0.0,"y":45.000003814697269,"z":0.0},"fullRotationData":[],"timelineAnimation":[],"bossSettings":[],"moveForward":[],"soData":[],"isChild":false},{"name":"extralargeBlock1","pos":{"x":9.600000381469727,"y":-1.5,"z":-23.700000762939454},"rot":{"x":0.0,"y":45.000003814697269,"z":0.0},"fullRotationData":[],"timelineAnimation":[],"bossSettings":[],"moveForward":[],"soData":[],"isChild":false},{"name":"extralargeBlock1","pos":{"x":-25.600000381469728,"y":-1.5,"z":15.699999809265137},"rot":{"x":0.0,"y":45.000003814697269,"z":0.0},"fullRotationData":[],"timelineAnimation":[],"bossSettings":[],"moveForward":[],"soData":[],"isChild":false},{"name":"extralargeBlock1","pos":{"x":24.799999237060548,"y":-1.5,"z":15.699999809265137},"rot":{"x":0.0,"y":45.000003814697269,"z":0.0},"fullRotationData":[],"timelineAnimation":[],"bossSettings":[],"moveForward":[],"soData":[],"isChild":false},{"name":"mediumBlock1","pos":{"x":0.0,"y":-1.5,"z":16.149999618530275},"rot":{"x":0.0,"y":0.0,"z":0.0},"fullRotationData":[],"timelineAnimation":[],"bossSettings":[],"moveForward":[],"soData":[],"isChild":false},{"name":"mediumBlock1","pos":{"x":0.0,"y":-1.5,"z":13.25},"rot":{"x":0.0,"y":0.0,"z":0.0},"fullRotationData":[],"timelineAnimation":[],"bossSettings":[],"moveForward":[],"soData":[],"isChild":false},{"name":"mediumBlock1","pos":{"x":0.0,"y":-1.5,"z":7.550000190734863},"rot":{"x":0.0,"y":0.0,"z":0.0},"fullRotationData":[],"timelineAnimation":[],"bossSettings":[],"moveForward":[],"soData":[],"isChild":false},{"name":"mediumBlock1","pos":{"x":0.0,"y":-1.5,"z":10.449999809265137},"rot":{"x":0.0,"y":0.0,"z":0.0},"fullRotationData":[],"timelineAnimation":[],"bossSettings":[],"moveForward":[],"soData":[],"isChild":false},{"name":"mediumBlock1","pos":{"x":0.0,"y":-1.5,"z":4.650000095367432},"rot":{"x":0.0,"y":0.0,"z":0.0},"fullRotationData":[],"timelineAnimation":[],"bossSettings":[],"moveForward":[],"soData":[],"isChild":false},{"name":"mediumBlock1","pos":{"x":0.0,"y":-1.5,"z":1.75},"rot":{"x":0.0,"y":0.0,"z":0.0},"fullRotationData":[],"timelineAnimation":[],"bossSettings":[],"moveForward":[],"soData":[],"isChild":false},{"name":"mediumBlock1","pos":{"x":0.0,"y":-1.5,"z":-4.050000190734863},"rot":{"x":0.0,"y":0.0,"z":0.0},"fullRotationData":[],"timelineAnimation":[],"bossSettings":[],"moveForward":[],"soData":[],"isChild":false},{"name":"mediumBlock1","pos":{"x":0.0,"y":-1.5,"z":-1.0499999523162842},"rot":{"x":0.0,"y":0.0,"z":0.0},"fullRotationData":[],"timelineAnimation":[],"bossSettings":[],"moveForward":[],"soData":[],"isChild":false},{"name":"mediumBlock1","pos":{"x":0.0,"y":-1.5,"z":-7.059999942779541},"rot":{"x":0.0,"y":0.0,"z":0.0},"fullRotationData":[],"timelineAnimation":[],"bossSettings":[],"moveForward":[],"soData":[],"isChild":false},{"name":"mediumBlock1","pos":{"x":0.0,"y":-1.5,"z":-9.970000267028809},"rot":{"x":0.0,"y":0.0,"z":0.0},"fullRotationData":[],"timelineAnimation":[],"bossSettings":[],"moveForward":[],"soData":[],"isChild":false},{"name":"mediumBlock1","pos":{"x":0.0,"y":-1.5,"z":-12.829999923706055},"rot":{"x":0.0,"y":0.0,"z":0.0},"fullRotationData":[],"timelineAnimation":[],"bossSettings":[],"moveForward":[],"soData":[],"isChild":false},{"name":"mediumBlock1","pos":{"x":0.0,"y":-1.5,"z":-15.699999809265137},"rot":{"x":0.0,"y":0.0,"z":0.0},"fullRotationData":[],"timelineAnimation":[],"bossSettings":[],"moveForward":[],"soData":[],"isChild":false},{"name":"mediumBlock1","pos":{"x":-9.600000381469727,"y":-1.5,"z":13.25},"rot":{"x":0.0,"y":0.0,"z":0.0},"fullRotationData":[],"timelineAnimation":[],"bossSettings":[],"moveForward":[],"soData":[],"isChild":false},{"name":"mediumBlock1","pos":{"x":-9.600000381469727,"y":-1.5,"z":7.550000190734863},"rot":{"x":0.0,"y":0.0,"z":0.0},"fullRotationData":[],"timelineAnimation":[],"bossSettings":[],"moveForward":[],"soData":[],"isChild":false},{"name":"mediumBlock1","pos":{"x":-10.0,"y":-1.5,"z":10.449999809265137},"rot":{"x":0.0,"y":0.0,"z":0.0},"fullRotationData":[],"timelineAnimation":[],"bossSettings":[],"moveForward":[],"soData":[],"isChild":false},{"name":"mediumBlock1","pos":{"x":-9.600000381469727,"y":-1.5,"z":4.650000095367432},"rot":{"x":0.0,"y":0.0,"z":0.0},"fullRotationData":[],"timelineAnimation":[],"bossSettings":[],"moveForward":[],"soData":[],"isChild":false},{"name":"mediumBlock1","pos":{"x":-9.600000381469727,"y":-1.5,"z":1.75},"rot":{"x":0.0,"y":0.0,"z":0.0},"fullRotationData":[],"timelineAnimation":[],"bossSettings":[],"moveForward":[],"soData":[],"isChild":false},{"name":"mediumBlock1","pos":{"x":-9.600000381469727,"y":-1.5,"z":-4.050000190734863},"rot":{"x":0.0,"y":0.0,"z":0.0},"fullRotationData":[],"timelineAnimation":[],"bossSettings":[],"moveForward":[],"soData":[],"isChild":false},{"name":"mediumBlock1","pos":{"x":-9.600000381469727,"y":-1.5,"z":-1.0499999523162842},"rot":{"x":0.0,"y":0.0,"z":0.0},"fullRotationData":[],"timelineAnimation":[],"bossSettings":[],"moveForward":[],"soData":[],"isChild":false},{"name":"mediumBlock1","pos":{"x":-9.600000381469727,"y":-1.5,"z":-7.059999942779541},"rot":{"x":0.0,"y":0.0,"z":0.0},"fullRotationData":[],"timelineAnimation":[],"bossSettings":[],"moveForward":[],"soData":[],"isChild":false},{"name":"mediumBlock1","pos":{"x":-9.600000381469727,"y":-1.5,"z":-9.970000267028809},"rot":{"x":0.0,"y":0.0,"z":0.0},"fullRotationData":[],"timelineAnimation":[],"bossSettings":[],"moveForward":[],"soData":[],"isChild":false},{"name":"mediumBlock1","pos":{"x":-9.600000381469727,"y":-1.5,"z":-12.829999923706055},"rot":{"x":0.0,"y":0.0,"z":0.0},"fullRotationData":[],"timelineAnimation":[],"bossSettings":[],"moveForward":[],"soData":[],"isChild":false},{"name":"mediumBlock1","pos":{"x":-9.600000381469727,"y":-1.5,"z":-15.699999809265137},"rot":{"x":0.0,"y":0.0,"z":0.0},"fullRotationData":[],"timelineAnimation":[],"bossSettings":[],"moveForward":[],"soData":[],"isChild":false},{"name":"mediumBlock1","pos":{"x":9.199999809265137,"y":-1.5,"z":16.149999618530275},"rot":{"x":0.0,"y":0.0,"z":0.0},"fullRotationData":[],"timelineAnimation":[],"bossSettings":[],"moveForward":[],"soData":[],"isChild":false},{"name":"mediumBlock1","pos":{"x":10.399999618530274,"y":-1.5,"z":13.25},"rot":{"x":0.0,"y":0.0,"z":0.0},"fullRotationData":[],"timelineAnimation":[],"bossSettings":[],"moveForward":[],"soData":[],"isChild":false},{"name":"mediumBlock1","pos":{"x":10.399999618530274,"y":-1.5,"z":7.550000190734863},"rot":{"x":0.0,"y":0.0,"z":0.0},"fullRotationData":[],"timelineAnimation":[],"bossSettings":[],"moveForward":[],"soData":[],"isChild":false},{"name":"mediumBlock1","pos":{"x":10.800000190734864,"y":-1.5,"z":10.449999809265137},"rot":{"x":0.0,"y":0.0,"z":0.0},"fullRotationData":[],"timelineAnimation":[],"bossSettings":[],"moveForward":[],"soData":[],"isChild":false},{"name":"mediumBlock1","pos":{"x":10.399999618530274,"y":-1.5,"z":4.650000095367432},"rot":{"x":0.0,"y":0.0,"z":0.0},"fullRotationData":[],"timelineAnimation":[],"bossSettings":[],"moveForward":[],"soData":[],"isChild":false},{"name":"mediumBlock1","pos":{"x":10.399999618530274,"y":-1.5,"z":1.75},"rot":{"x":0.0,"y":0.0,"z":0.0},"fullRotationData":[],"timelineAnimation":[],"bossSettings":[],"moveForward":[],"soData":[],"isChild":false},{"name":"mediumBlock1","pos":{"x":10.399999618530274,"y":-1.5,"z":-4.050000190734863},"rot":{"x":0.0,"y":0.0,"z":0.0},"fullRotationData":[],"timelineAnimation":[],"bossSettings":[],"moveForward":[],"soData":[],"isChild":false},{"name":"mediumBlock1","pos":{"x":10.399999618530274,"y":-1.5,"z":-1.0499999523162842},"rot":{"x":0.0,"y":0.0,"z":0.0},"fullRotationData":[],"timelineAnimation":[],"bossSettings":[],"moveForward":[],"soData":[],"isChild":false},{"name":"mediumBlock1","pos":{"x":10.399999618530274,"y":-1.5,"z":-7.059999942779541},"rot":{"x":0.0,"y":0.0,"z":0.0},"fullRotationData":[],"timelineAnimation":[],"bossSettings":[],"moveForward":[],"soData":[],"isChild":false},{"name":"mediumBlock1","pos":{"x":10.399999618530274,"y":-1.5,"z":-9.970000267028809},"rot":{"x":0.0,"y":0.0,"z":0.0},"fullRotationData":[],"timelineAnimation":[],"bossSettings":[],"moveForward":[],"soData":[],"isChild":false},{"name":"mediumBlock1","pos":{"x":10.399999618530274,"y":-1.5,"z":-12.829999923706055},"rot":{"x":0.0,"y":0.0,"z":0.0},"fullRotationData":[],"timelineAnimation":[],"bossSettings":[],"moveForward":[],"soData":[],"isChild":false},{"name":"mediumBlock1","pos":{"x":10.399999618530274,"y":-1.5,"z":-15.699999809265137},"rot":{"x":0.0,"y":0.0,"z":0.0},"fullRotationData":[],"timelineAnimation":[],"bossSettings":[],"moveForward":[],"soData":[],"isChild":false},{"name":"palmTall","pos":{"x":-20.700000762939454,"y":-1.1399999856948853,"z":15.399999618530274},"rot":{"x":0.0,"y":180.0,"z":0.0},"fullRotationData":[],"timelineAnimation":[],"bossSettings":[],"moveForward":[],"soData":[],"isChild":false},{"name":"palmTall","pos":{"x":21.399999618530275,"y":-1.1399999856948853,"z":15.399999618530274},"rot":{"x":0.0,"y":0.0,"z":0.0},"fullRotationData":[],"timelineAnimation":[],"bossSettings":[],"moveForward":[],"soData":[],"isChild":false},{"name":"palmTall","pos":{"x":-28.299999237060548,"y":-1.1399999856948853,"z":15.399999618530274},"rot":{"x":0.0,"y":180.0,"z":0.0},"fullRotationData":[],"timelineAnimation":[],"bossSettings":[],"moveForward":[],"soData":[],"isChild":false},{"name":"palmTall","pos":{"x":-25.100000381469728,"y":-1.1399999856948853,"z":10.600000381469727},"rot":{"x":0.0,"y":180.0,"z":0.0},"fullRotationData":[],"timelineAnimation":[],"bossSettings":[],"moveForward":[],"soData":[],"isChild":false},{"name":"palmTall","pos":{"x":29.399999618530275,"y":-1.1399999856948853,"z":15.399999618530274},"rot":{"x":0.0,"y":0.0,"z":0.0},"fullRotationData":[],"timelineAnimation":[],"bossSettings":[],"moveForward":[],"soData":[],"isChild":false},{"name":"palmTall","pos":{"x":25.0,"y":-1.1399999856948853,"z":10.600000381469727},"rot":{"x":0.0,"y":0.0,"z":0.0},"fullRotationData":[],"timelineAnimation":[],"bossSettings":[],"moveForward":[],"soData":[],"isChild":false},{"name":"BossCreator","pos":{"x":0.0,"y":1.899999976158142,"z":-8.899999618530274},"rot":{"x":0.0,"y":0.0,"z":0.0},"fullRotationData":[],"timelineAnimation":[],"bossSettings":[{"bossModule":"Mov8","time_to_init_enemies":0.4000000059604645,"asset":"nave_ojos2","distance_from_avatars":18.0,"time_to_kill":50}],"moveForward":[],"soData":[],"isChild":false},{"name":"mediumBlock1","pos":{"x":-10.0,"y":-1.5,"z":22.600000381469728},"rot":{"x":0.0,"y":0.0,"z":0.0},"fullRotationData":[],"timelineAnimation":[],"bossSettings":[],"moveForward":[],"soData":[],"isChild":false},{"name":"mediumBlock1","pos":{"x":0.0,"y":-1.5,"z":22.600000381469728},"rot":{"x":0.0,"y":0.0,"z":0.0},"fullRotationData":[],"timelineAnimation":[],"bossSettings":[],"moveForward":[],"soData":[],"isChild":false},{"name":"mediumBlock1","pos":{"x":10.0,"y":-1.5,"z":22.600000381469728},"rot":{"x":0.0,"y":0.0,"z":0.0},"fullRotationData":[],"timelineAnimation":[],"bossSettings":[],"moveForward":[],"soData":[],"isChild":false},{"name":"mediumBlock1","pos":{"x":-10.0,"y":-1.5,"z":25.6200008392334},"rot":{"x":0.0,"y":0.0,"z":0.0},"fullRotationData":[],"timelineAnimation":[],"bossSettings":[],"moveForward":[],"soData":[],"isChild":false},{"name":"mediumBlock1","pos":{"x":0.0,"y":-1.5,"z":25.6200008392334},"rot":{"x":0.0,"y":0.0,"z":0.0},"fullRotationData":[],"timelineAnimation":[],"bossSettings":[],"moveForward":[],"soData":[],"isChild":false},{"name":"mediumBlock1","pos":{"x":10.0,"y":-1.5,"z":25.6200008392334},"rot":{"x":0.0,"y":0.0,"z":0.0},"fullRotationData":[],"timelineAnimation":[],"bossSettings":[],"moveForward":[],"soData":[],"isChild":false},{"name":"mediumBlock1","pos":{"x":-8.979999542236329,"y":-1.5,"z":16.450000762939454},"rot":{"x":0.0,"y":0.0,"z":0.0},"fullRotationData":[],"timelineAnimation":[],"bossSettings":[],"moveForward":[],"soData":[],"isChild":false},{"name":"mediumBlock1","pos":{"x":-11.0,"y":-1.5,"z":19.600000381469728},"rot":{"x":0.0,"y":0.0,"z":0.0},"fullRotationData":[],"timelineAnimation":[],"bossSettings":[],"moveForward":[],"soData":[],"isChild":false},{"name":"mediumBlock1","pos":{"x":0.6000000238418579,"y":-1.5,"z":19.299999237060548},"rot":{"x":0.0,"y":0.0,"z":0.0},"fullRotationData":[],"timelineAnimation":[],"bossSettings":[],"moveForward":[],"soData":[],"isChild":false},{"name":"mediumBlock1","pos":{"x":10.600000381469727,"y":-1.5,"z":19.600000381469728},"rot":{"x":0.0,"y":0.0,"z":0.0},"fullRotationData":[],"timelineAnimation":[],"bossSettings":[],"moveForward":[],"soData":[],"isChild":false}]}