{"totalCoins":36,"z_length":110.0,"data":[{"name":"extralargeBlock1","pos":{"x":0.0,"y":-1.5,"z":-39.27000045776367},"rot":{"x":0.0,"y":0.0,"z":0.0},"fullRotationData":[],"timelineAnimation":[],"bossSettings":[],"moveForward":[],"soData":[],"isChild":false},{"name":"palm","pos":{"x":5.0,"y":-0.8999999761581421,"z":-42.970001220703128},"rot":{"x":0.0,"y":90.0,"z":0.0},"fullRotationData":[],"timelineAnimation":[],"bossSettings":[],"moveForward":[],"soData":[],"isChild":false},{"name":"FloorSlider","pos":{"x":3.200000047683716,"y":0.0,"z":-20.0},"rot":{"x":0.0,"y":180.0,"z":0.0},"fullRotationData":[],"timelineAnimation":[],"bossSettings":[],"moveForward":[],"soData":[],"isChild":false},{"name":"FloorSlider","pos":{"x":3.200000047683716,"y":0.0,"z":-29.0},"rot":{"x":0.0,"y":180.0,"z":0.0},"fullRotationData":[],"timelineAnimation":[],"bossSettings":[],"moveForward":[],"soData":[],"isChild":false},{"name":"FloorSlider","pos":{"x":3.200000047683716,"y":0.0,"z":-11.0},"rot":{"x":0.0,"y":180.0,"z":0.0},"fullRotationData":[],"timelineAnimation":[],"bossSettings":[],"moveForward":[],"soData":[],"isChild":false},{"name":"largeBlock1","pos":{"x":-3.5999999046325685,"y":-2.049999952316284,"z":-7.599999904632568},"rot":{"x":0.0,"y":0.0,"z":0.0},"fullRotationData":[],"timelineAnimation":[],"bossSettings":[],"moveForward":[],"soData":[],"isChild":false},{"name":"largeBlock1","pos":{"x":-3.5999999046325685,"y":-2.049999952316284,"z":-13.600000381469727},"rot":{"x":0.0,"y":0.0,"z":0.0},"fullRotationData":[],"timelineAnimation":[],"bossSettings":[],"moveForward":[],"soData":[],"isChild":false},{"name":"largeBlock1","pos":{"x":-3.5999999046325685,"y":-2.049999952316284,"z":-19.600000381469728},"rot":{"x":0.0,"y":0.0,"z":0.0},"fullRotationData":[],"timelineAnimation":[],"bossSettings":[],"moveForward":[],"soData":[],"isChild":false},{"name":"largeBlock1","pos":{"x":-3.5999999046325685,"y":-2.049999952316284,"z":-25.600000381469728},"rot":{"x":0.0,"y":0.0,"z":0.0},"fullRotationData":[],"timelineAnimation":[],"bossSettings":[],"moveForward":[],"soData":[],"isChild":false},{"name":"largeBlock1","pos":{"x":-3.5999999046325685,"y":-2.049999952316284,"z":-31.600000381469728},"rot":{"x":0.0,"y":0.0,"z":0.0},"fullRotationData":[],"timelineAnimation":[],"bossSettings":[],"moveForward":[],"soData":[],"isChild":false},{"name":"enemyFrontal","pos":{"x":-3.0999999046325685,"y":1.600000023841858,"z":0.6700000166893005},"rot":{"x":0.0,"y":180.0,"z":0.0},"fullRotationData":[],"timelineAnimation":[],"bossSettings":[],"moveForward":[{"speed":5.0,"randomSpeedDiff":0.0,"moveBackIn":0.0}],"soData":[],"isChild":false},{"name":"enemyFrontal","pos":{"x":3.5,"y":1.600000023841858,"z":-4.71999979019165},"rot":{"x":0.0,"y":0.0,"z":0.0},"fullRotationData":[],"timelineAnimation":[],"bossSettings":[],"moveForward":[{"speed":5.0,"randomSpeedDiff":0.0,"moveBackIn":0.0}],"soData":[],"isChild":false},{"name":"extralargeBlock1","pos":{"x":0.0,"y":-1.5,"z":-0.5},"rot":{"x":0.0,"y":0.0,"z":0.0},"fullRotationData":[],"timelineAnimation":[],"bossSettings":[],"moveForward":[],"soData":[],"isChild":false},{"name":"extralargeBlock1","pos":{"x":0.0,"y":-1.5,"z":38.29999923706055},"rot":{"x":0.0,"y":0.0,"z":0.0},"fullRotationData":[],"timelineAnimation":[],"bossSettings":[],"moveForward":[],"soData":[],"isChild":false},{"name":"FloorSlider","pos":{"x":-2.799999952316284,"y":0.0,"z":19.100000381469728},"rot":{"x":0.0,"y":0.0,"z":0.0},"fullRotationData":[],"timelineAnimation":[],"bossSettings":[],"moveForward":[],"soData":[],"isChild":false},{"name":"FloorSlider","pos":{"x":-2.799999952316284,"y":0.0,"z":10.100000381469727},"rot":{"x":0.0,"y":0.0,"z":0.0},"fullRotationData":[],"timelineAnimation":[],"bossSettings":[],"moveForward":[],"soData":[],"isChild":false},{"name":"FloorSlider","pos":{"x":-2.799999952316284,"y":0.0,"z":27.899999618530275},"rot":{"x":0.0,"y":0.0,"z":0.0},"fullRotationData":[],"timelineAnimation":[],"bossSettings":[],"moveForward":[],"soData":[],"isChild":false},{"name":"largeBlock1","pos":{"x":4.0,"y":-2.049999952316284,"z":26.0},"rot":{"x":0.0,"y":0.0,"z":0.0},"fullRotationData":[],"timelineAnimation":[],"bossSettings":[],"moveForward":[],"soData":[],"isChild":false},{"name":"largeBlock1","pos":{"x":4.0,"y":-2.049999952316284,"z":8.0},"rot":{"x":0.0,"y":0.0,"z":0.0},"fullRotationData":[],"timelineAnimation":[],"bossSettings":[],"moveForward":[],"soData":[],"isChild":false},{"name":"largeBlock1","pos":{"x":4.0,"y":-2.049999952316284,"z":32.0},"rot":{"x":0.0,"y":0.0,"z":0.0},"fullRotationData":[],"timelineAnimation":[],"bossSettings":[],"moveForward":[],"soData":[],"isChild":false},{"name":"largeBlock1","pos":{"x":4.0,"y":-2.049999952316284,"z":20.0},"rot":{"x":0.0,"y":0.0,"z":0.0},"fullRotationData":[],"timelineAnimation":[],"bossSettings":[],"moveForward":[],"soData":[],"isChild":false},{"name":"largeBlock1","pos":{"x":4.0,"y":-2.049999952316284,"z":14.0},"rot":{"x":0.0,"y":0.0,"z":0.0},"fullRotationData":[],"timelineAnimation":[],"bossSettings":[],"moveForward":[],"soData":[],"isChild":false},{"name":"Coin","pos":{"x":2.0,"y":0.10000000149011612,"z":-23.1200008392334},"rot":{"x":0.0,"y":0.0,"z":0.0},"fullRotationData":[],"timelineAnimation":[],"bossSettings":[],"moveForward":[],"soData":[],"isChild":false},{"name":"Coin","pos":{"x":2.0,"y":0.10000000149011612,"z":-21.520000457763673},"rot":{"x":0.0,"y":0.0,"z":0.0},"fullRotationData":[],"timelineAnimation":[],"bossSettings":[],"moveForward":[],"soData":[],"isChild":false},{"name":"Coin","pos":{"x":2.0,"y":0.10000000149011612,"z":-19.920000076293947},"rot":{"x":0.0,"y":0.0,"z":0.0},"fullRotationData":[],"timelineAnimation":[],"bossSettings":[],"moveForward":[],"soData":[],"isChild":false},{"name":"Coin","pos":{"x":2.0,"y":0.10000000149011612,"z":-18.31999969482422},"rot":{"x":0.0,"y":0.0,"z":0.0},"fullRotationData":[],"timelineAnimation":[],"bossSettings":[],"moveForward":[],"soData":[],"isChild":false},{"name":"Coin","pos":{"x":2.0,"y":0.10000000149011612,"z":-16.719999313354493},"rot":{"x":0.0,"y":0.0,"z":0.0},"fullRotationData":[],"timelineAnimation":[],"bossSettings":[],"moveForward":[],"soData":[],"isChild":false},{"name":"Coin","pos":{"x":2.0,"y":0.10000000149011612,"z":-15.119999885559082},"rot":{"x":0.0,"y":0.0,"z":0.0},"fullRotationData":[],"timelineAnimation":[],"bossSettings":[],"moveForward":[],"soData":[],"isChild":false},{"name":"Coin","pos":{"x":3.200000047683716,"y":0.10000000149011612,"z":-23.1200008392334},"rot":{"x":0.0,"y":0.0,"z":0.0},"fullRotationData":[],"timelineAnimation":[],"bossSettings":[],"moveForward":[],"soData":[],"isChild":false},{"name":"Coin","pos":{"x":3.200000047683716,"y":0.10000000149011612,"z":-21.520000457763673},"rot":{"x":0.0,"y":0.0,"z":0.0},"fullRotationData":[],"timelineAnimation":[],"bossSettings":[],"moveForward":[],"soData":[],"isChild":false},{"name":"Coin","pos":{"x":3.200000047683716,"y":0.10000000149011612,"z":-19.920000076293947},"rot":{"x":0.0,"y":0.0,"z":0.0},"fullRotationData":[],"timelineAnimation":[],"bossSettings":[],"moveForward":[],"soData":[],"isChild":false},{"name":"Coin","pos":{"x":3.200000047683716,"y":0.10000000149011612,"z":-18.31999969482422},"rot":{"x":0.0,"y":0.0,"z":0.0},"fullRotationData":[],"timelineAnimation":[],"bossSettings":[],"moveForward":[],"soData":[],"isChild":false},{"name":"Coin","pos":{"x":3.200000047683716,"y":0.10000000149011612,"z":-16.719999313354493},"rot":{"x":0.0,"y":0.0,"z":0.0},"fullRotationData":[],"timelineAnimation":[],"bossSettings":[],"moveForward":[],"soData":[],"isChild":false},{"name":"Coin","pos":{"x":3.200000047683716,"y":0.10000000149011612,"z":-15.119999885559082},"rot":{"x":0.0,"y":0.0,"z":0.0},"fullRotationData":[],"timelineAnimation":[],"bossSettings":[],"moveForward":[],"soData":[],"isChild":false},{"name":"house2","pos":{"x":-2.4000000953674318,"y":0.10000000149011612,"z":41.400001525878909},"rot":{"x":0.0,"y":0.0,"z":0.0},"fullRotationData":[],"timelineAnimation":[],"bossSettings":[],"moveForward":[],"soData":[],"isChild":false},{"name":"Coin","pos":{"x":4.400000095367432,"y":0.10000000149011612,"z":-23.1200008392334},"rot":{"x":0.0,"y":0.0,"z":0.0},"fullRotationData":[],"timelineAnimation":[],"bossSettings":[],"moveForward":[],"soData":[],"isChild":false},{"name":"Coin","pos":{"x":4.400000095367432,"y":0.10000000149011612,"z":-21.520000457763673},"rot":{"x":0.0,"y":0.0,"z":0.0},"fullRotationData":[],"timelineAnimation":[],"bossSettings":[],"moveForward":[],"soData":[],"isChild":false},{"name":"Coin","pos":{"x":4.400000095367432,"y":0.10000000149011612,"z":-19.920000076293947},"rot":{"x":0.0,"y":0.0,"z":0.0},"fullRotationData":[],"timelineAnimation":[],"bossSettings":[],"moveForward":[],"soData":[],"isChild":false},{"name":"Coin","pos":{"x":4.400000095367432,"y":0.10000000149011612,"z":-18.31999969482422},"rot":{"x":0.0,"y":0.0,"z":0.0},"fullRotationData":[],"timelineAnimation":[],"bossSettings":[],"moveForward":[],"soData":[],"isChild":false},{"name":"Coin","pos":{"x":4.400000095367432,"y":0.10000000149011612,"z":-16.719999313354493},"rot":{"x":0.0,"y":0.0,"z":0.0},"fullRotationData":[],"timelineAnimation":[],"bossSettings":[],"moveForward":[],"soData":[],"isChild":false},{"name":"Coin","pos":{"x":4.400000095367432,"y":0.10000000149011612,"z":-15.119999885559082},"rot":{"x":0.0,"y":0.0,"z":0.0},"fullRotationData":[],"timelineAnimation":[],"bossSettings":[],"moveForward":[],"soData":[],"isChild":false},{"name":"Coin","pos":{"x":-4.0,"y":0.10000000149011612,"z":14.479999542236329},"rot":{"x":0.0,"y":0.0,"z":0.0},"fullRotationData":[],"timelineAnimation":[],"bossSettings":[],"moveForward":[],"soData":[],"isChild":false},{"name":"Coin","pos":{"x":-4.0,"y":0.10000000149011612,"z":16.079999923706056},"rot":{"x":0.0,"y":0.0,"z":0.0},"fullRotationData":[],"timelineAnimation":[],"bossSettings":[],"moveForward":[],"soData":[],"isChild":false},{"name":"Coin","pos":{"x":-4.0,"y":0.10000000149011612,"z":17.68000030517578},"rot":{"x":0.0,"y":0.0,"z":0.0},"fullRotationData":[],"timelineAnimation":[],"bossSettings":[],"moveForward":[],"soData":[],"isChild":false},{"name":"Coin","pos":{"x":-4.0,"y":0.10000000149011612,"z":19.280000686645509},"rot":{"x":0.0,"y":0.0,"z":0.0},"fullRotationData":[],"timelineAnimation":[],"bossSettings":[],"moveForward":[],"soData":[],"isChild":false},{"name":"Coin","pos":{"x":-4.0,"y":0.10000000149011612,"z":20.8799991607666},"rot":{"x":0.0,"y":0.0,"z":0.0},"fullRotationData":[],"timelineAnimation":[],"bossSettings":[],"moveForward":[],"soData":[],"isChild":false},{"name":"Coin","pos":{"x":-4.0,"y":0.10000000149011612,"z":22.479999542236329},"rot":{"x":0.0,"y":0.0,"z":0.0},"fullRotationData":[],"timelineAnimation":[],"bossSettings":[],"moveForward":[],"soData":[],"isChild":false},{"name":"Coin","pos":{"x":-2.799999952316284,"y":0.10000000149011612,"z":14.479999542236329},"rot":{"x":0.0,"y":0.0,"z":0.0},"fullRotationData":[],"timelineAnimation":[],"bossSettings":[],"moveForward":[],"soData":[],"isChild":false},{"name":"Coin","pos":{"x":-2.799999952316284,"y":0.10000000149011612,"z":16.079999923706056},"rot":{"x":0.0,"y":0.0,"z":0.0},"fullRotationData":[],"timelineAnimation":[],"bossSettings":[],"moveForward":[],"soData":[],"isChild":false},{"name":"Coin","pos":{"x":-2.799999952316284,"y":0.10000000149011612,"z":17.68000030517578},"rot":{"x":0.0,"y":0.0,"z":0.0},"fullRotationData":[],"timelineAnimation":[],"bossSettings":[],"moveForward":[],"soData":[],"isChild":false},{"name":"Coin","pos":{"x":-2.799999952316284,"y":0.10000000149011612,"z":19.280000686645509},"rot":{"x":0.0,"y":0.0,"z":0.0},"fullRotationData":[],"timelineAnimation":[],"bossSettings":[],"moveForward":[],"soData":[],"isChild":false},{"name":"Coin","pos":{"x":-2.799999952316284,"y":0.10000000149011612,"z":20.8799991607666},"rot":{"x":0.0,"y":0.0,"z":0.0},"fullRotationData":[],"timelineAnimation":[],"bossSettings":[],"moveForward":[],"soData":[],"isChild":false},{"name":"Coin","pos":{"x":-2.799999952316284,"y":0.10000000149011612,"z":22.479999542236329},"rot":{"x":0.0,"y":0.0,"z":0.0},"fullRotationData":[],"timelineAnimation":[],"bossSettings":[],"moveForward":[],"soData":[],"isChild":false},{"name":"Coin","pos":{"x":-1.600000023841858,"y":0.10000000149011612,"z":14.479999542236329},"rot":{"x":0.0,"y":0.0,"z":0.0},"fullRotationData":[],"timelineAnimation":[],"bossSettings":[],"moveForward":[],"soData":[],"isChild":false},{"name":"Coin","pos":{"x":-1.600000023841858,"y":0.10000000149011612,"z":16.079999923706056},"rot":{"x":0.0,"y":0.0,"z":0.0},"fullRotationData":[],"timelineAnimation":[],"bossSettings":[],"moveForward":[],"soData":[],"isChild":false},{"name":"Coin","pos":{"x":-1.600000023841858,"y":0.10000000149011612,"z":17.68000030517578},"rot":{"x":0.0,"y":0.0,"z":0.0},"fullRotationData":[],"timelineAnimation":[],"bossSettings":[],"moveForward":[],"soData":[],"isChild":false},{"name":"Coin","pos":{"x":-1.600000023841858,"y":0.10000000149011612,"z":19.280000686645509},"rot":{"x":0.0,"y":0.0,"z":0.0},"fullRotationData":[],"timelineAnimation":[],"bossSettings":[],"moveForward":[],"soData":[],"isChild":false},{"name":"Coin","pos":{"x":-1.600000023841858,"y":0.10000000149011612,"z":20.8799991607666},"rot":{"x":0.0,"y":0.0,"z":0.0},"fullRotationData":[],"timelineAnimation":[],"bossSettings":[],"moveForward":[],"soData":[],"isChild":false},{"name":"Coin","pos":{"x":-1.600000023841858,"y":0.10000000149011612,"z":22.479999542236329},"rot":{"x":0.0,"y":0.0,"z":0.0},"fullRotationData":[],"timelineAnimation":[],"bossSettings":[],"moveForward":[],"soData":[],"isChild":false},{"name":"palm","pos":{"x":-4.599999904632568,"y":-0.8999999761581421,"z":-42.970001220703128},"rot":{"x":0.0,"y":90.0,"z":0.0},"fullRotationData":[],"timelineAnimation":[],"bossSettings":[],"moveForward":[],"soData":[],"isChild":false},{"name":"palm","pos":{"x":-3.799999952316284,"y":-0.8999999761581421,"z":-39.77000045776367},"rot":{"x":0.0,"y":90.0,"z":0.0},"fullRotationData":[],"timelineAnimation":[],"bossSettings":[],"moveForward":[],"soData":[],"isChild":false},{"name":"palm","pos":{"x":4.800000190734863,"y":-0.8999999761581421,"z":0.20000000298023225},"rot":{"x":0.0,"y":90.0,"z":0.0},"fullRotationData":[],"timelineAnimation":[],"bossSettings":[],"moveForward":[],"soData":[],"isChild":false},{"name":"palm","pos":{"x":3.5999999046325685,"y":-0.8999999761581421,"z":3.4000000953674318},"rot":{"x":0.0,"y":90.0,"z":0.0},"fullRotationData":[],"timelineAnimation":[],"bossSettings":[],"moveForward":[],"soData":[],"isChild":false},{"name":"house2","pos":{"x":2.799999952316284,"y":0.10000000149011612,"z":41.400001525878909},"rot":{"x":0.0,"y":0.0,"z":0.0},"fullRotationData":[],"timelineAnimation":[],"bossSettings":[],"moveForward":[],"soData":[],"isChild":false}]}