{"totalCoins":20,"z_length":6.0,"data":[{"name":"Container","pos":{"x":0.0,"y":0.0,"z":0.0},"rot":{"x":0.0,"y":0.0,"z":340.0},"fullRotationData":[],"timelineAnimation":[{"timeLineData":[{"move":false,"rotate":true,"duration":2.0,"data":{"x":0.0,"y":0.0,"z":40.0},"easeType":1},{"move":false,"rotate":true,"duration":2.0,"data":{"x":0.0,"y":0.0,"z":0.0},"easeType":1}]}],"bossSettings":[],"moveForward":[],"soData":[],"isChild":false},{"name":"palm","pos":{"x":-17.18000030517578,"y":6.889999866485596,"z":-1.399999976158142},"rot":{"x":-0.000012677378435910214,"y":180.00001525878907,"z":19.999990463256837},"fullRotationData":[],"timelineAnimation":[],"bossSettings":[],"moveForward":[],"soData":[],"isChild":true},{"name":"largeBlock1","pos":{"x":0.0,"y":0.0,"z":0.0},"rot":{"x":0.0,"y":0.0,"z":340.0},"fullRotationData":[],"timelineAnimation":[],"bossSettings":[],"moveForward":[],"soData":[],"isChild":true},{"name":"largeBlock1","pos":{"x":5.639999866485596,"y":-2.049999952316284,"z":0.0},"rot":{"x":0.0,"y":0.0,"z":340.0},"fullRotationData":[],"timelineAnimation":[],"bossSettings":[],"moveForward":[],"soData":[],"isChild":true},{"name":"largeBlock1","pos":{"x":11.270000457763672,"y":-4.099999904632568,"z":0.0},"rot":{"x":0.0,"y":0.0,"z":340.0},"fullRotationData":[],"timelineAnimation":[],"bossSettings":[],"moveForward":[],"soData":[],"isChild":true},{"name":"largeBlock1","pos":{"x":16.920000076293947,"y":-6.159999847412109,"z":0.0},"rot":{"x":0.0,"y":0.0,"z":340.0},"fullRotationData":[],"timelineAnimation":[],"bossSettings":[],"moveForward":[],"soData":[],"isChild":true},{"name":"largeBlock1","pos":{"x":-5.639999866485596,"y":2.049999952316284,"z":0.0},"rot":{"x":0.0,"y":0.0,"z":340.0},"fullRotationData":[],"timelineAnimation":[],"bossSettings":[],"moveForward":[],"soData":[],"isChild":true},{"name":"largeBlock1","pos":{"x":-11.270000457763672,"y":4.099999904632568,"z":0.0},"rot":{"x":0.0,"y":0.0,"z":340.0},"fullRotationData":[],"timelineAnimation":[],"bossSettings":[],"moveForward":[],"soData":[],"isChild":true},{"name":"largeBlock1","pos":{"x":-16.920000076293947,"y":6.159999847412109,"z":0.0},"rot":{"x":0.0,"y":0.0,"z":340.0},"fullRotationData":[],"timelineAnimation":[],"bossSettings":[],"moveForward":[],"soData":[],"isChild":true},{"name":"enemyFrontal","pos":{"x":-13.729999542236329,"y":6.710000038146973,"z":0.0},"rot":{"x":339.9999694824219,"y":270.0,"z":0.0},"fullRotationData":[],"timelineAnimation":[],"bossSettings":[],"moveForward":[{"speed":-6.0,"randomSpeedDiff":2.0,"moveBackIn":0.0}],"soData":[],"isChild":true},{"name":"Coin","pos":{"x":11.350000381469727,"y":-1.5700000524520875,"z":0.0},"rot":{"x":0.0,"y":0.0,"z":340.0},"fullRotationData":[],"timelineAnimation":[],"bossSettings":[],"moveForward":[],"soData":[],"isChild":true},{"name":"Coin","pos":{"x":9.470000267028809,"y":-0.8899999856948853,"z":0.0},"rot":{"x":0.0,"y":0.0,"z":340.0},"fullRotationData":[],"timelineAnimation":[],"bossSettings":[],"moveForward":[],"soData":[],"isChild":true},{"name":"Coin","pos":{"x":7.960000038146973,"y":-0.3400000035762787,"z":0.0},"rot":{"x":0.0,"y":0.0,"z":340.0},"fullRotationData":[],"timelineAnimation":[],"bossSettings":[],"moveForward":[],"soData":[],"isChild":true},{"name":"Coin","pos":{"x":6.079999923706055,"y":0.3400000035762787,"z":0.0},"rot":{"x":0.0,"y":0.0,"z":340.0},"fullRotationData":[],"timelineAnimation":[],"bossSettings":[],"moveForward":[],"soData":[],"isChild":true},{"name":"Coin","pos":{"x":4.210000038146973,"y":1.0299999713897706,"z":0.0},"rot":{"x":0.0,"y":0.0,"z":340.0},"fullRotationData":[],"timelineAnimation":[],"bossSettings":[],"moveForward":[],"soData":[],"isChild":true},{"name":"Coin","pos":{"x":2.3299999237060549,"y":1.7100000381469727,"z":0.0},"rot":{"x":0.0,"y":0.0,"z":340.0},"fullRotationData":[],"timelineAnimation":[],"bossSettings":[],"moveForward":[],"soData":[],"isChild":true},{"name":"Coin","pos":{"x":0.4399999976158142,"y":2.390000104904175,"z":0.0},"rot":{"x":0.0,"y":0.0,"z":340.0},"fullRotationData":[],"timelineAnimation":[],"bossSettings":[],"moveForward":[],"soData":[],"isChild":true},{"name":"Coin","pos":{"x":-1.440000057220459,"y":3.0799999237060549,"z":0.0},"rot":{"x":0.0,"y":0.0,"z":340.0},"fullRotationData":[],"timelineAnimation":[],"bossSettings":[],"moveForward":[],"soData":[],"isChild":true},{"name":"Coin","pos":{"x":-3.309999942779541,"y":3.759999990463257,"z":0.0},"rot":{"x":0.0,"y":0.0,"z":340.0},"fullRotationData":[],"timelineAnimation":[],"bossSettings":[],"moveForward":[],"soData":[],"isChild":true},{"name":"Coin","pos":{"x":-5.190000057220459,"y":4.449999809265137,"z":0.0},"rot":{"x":0.0,"y":0.0,"z":340.0},"fullRotationData":[],"timelineAnimation":[],"bossSettings":[],"moveForward":[],"soData":[],"isChild":true},{"name":"Coin","pos":{"x":11.760000228881836,"y":-0.44999998807907107,"z":0.0},"rot":{"x":0.0,"y":0.0,"z":340.0},"fullRotationData":[],"timelineAnimation":[],"bossSettings":[],"moveForward":[],"soData":[],"isChild":true},{"name":"Coin","pos":{"x":9.880000114440918,"y":0.23999999463558198,"z":0.0},"rot":{"x":0.0,"y":0.0,"z":340.0},"fullRotationData":[],"timelineAnimation":[],"bossSettings":[],"moveForward":[],"soData":[],"isChild":true},{"name":"Coin","pos":{"x":8.369999885559082,"y":0.7900000214576721,"z":0.0},"rot":{"x":0.0,"y":0.0,"z":340.0},"fullRotationData":[],"timelineAnimation":[],"bossSettings":[],"moveForward":[],"soData":[],"isChild":true},{"name":"Coin","pos":{"x":6.489999771118164,"y":1.4700000286102296,"z":0.0},"rot":{"x":0.0,"y":0.0,"z":340.0},"fullRotationData":[],"timelineAnimation":[],"bossSettings":[],"moveForward":[],"soData":[],"isChild":true},{"name":"Coin","pos":{"x":4.619999885559082,"y":2.1500000953674318,"z":0.0},"rot":{"x":0.0,"y":0.0,"z":340.0},"fullRotationData":[],"timelineAnimation":[],"bossSettings":[],"moveForward":[],"soData":[],"isChild":true},{"name":"Coin","pos":{"x":2.740000009536743,"y":2.8399999141693117,"z":0.0},"rot":{"x":0.0,"y":0.0,"z":340.0},"fullRotationData":[],"timelineAnimation":[],"bossSettings":[],"moveForward":[],"soData":[],"isChild":true},{"name":"Coin","pos":{"x":0.8500000238418579,"y":3.5199999809265138,"z":0.0},"rot":{"x":0.0,"y":0.0,"z":340.0},"fullRotationData":[],"timelineAnimation":[],"bossSettings":[],"moveForward":[],"soData":[],"isChild":true},{"name":"Coin","pos":{"x":-1.0299999713897706,"y":4.210000038146973,"z":0.0},"rot":{"x":0.0,"y":0.0,"z":340.0},"fullRotationData":[],"timelineAnimation":[],"bossSettings":[],"moveForward":[],"soData":[],"isChild":true},{"name":"Coin","pos":{"x":-2.9000000953674318,"y":4.889999866485596,"z":0.0},"rot":{"x":0.0,"y":0.0,"z":340.0},"fullRotationData":[],"timelineAnimation":[],"bossSettings":[],"moveForward":[],"soData":[],"isChild":true},{"name":"Coin","pos":{"x":-4.78000020980835,"y":5.570000171661377,"z":0.0},"rot":{"x":0.0,"y":0.0,"z":340.0},"fullRotationData":[],"timelineAnimation":[],"bossSettings":[],"moveForward":[],"soData":[],"isChild":true},{"name":"palm","pos":{"x":-17.639999389648439,"y":7.059999942779541,"z":1.5},"rot":{"x":-0.000012677378435910214,"y":180.00001525878907,"z":19.999990463256837},"fullRotationData":[],"timelineAnimation":[],"bossSettings":[],"moveForward":[],"soData":[],"isChild":true}]}