{
	"data": [{
		"title": "UNBREAKABLE FIREWALLS",
		"fondo": "gallax",
		"id": 0,
		"maxScore": 0,
		"areaSetData": [		
		{
			"total_areas": 1,
			"randomize": false,
			"areas": [
			"container_descanso_cruz",
			"firewallsSimple"
			],
			"cameraOrientation": {
				"x": 0.0,
				"y": 2.0,
				"z": 0.0
			}
		},	
		{
			"total_areas": 4,
			"randomize": true,
			"areas": [
			"firewallsSimple",
			"firewallsSimple2"
			],
			"cameraOrientation": {
				"x": 0.0,
				"y": -3.0,
				"z": -2.0
			}
		},
		{
			"total_areas": 1,
			"randomize": true,
			"areas": [
			"firewalls_lasers"
			],
			"cameraOrientation": {
				"x": 0.0,
				"y": -3.0,
				"z": -2.0
			}
		},
		{
			"total_areas": 1,
			"randomize": true,
			"areas": [
			"container_firewalls"
			],
			"cameraOrientation": {
				"x": 0.0,
				"y": 0.0,
				"z": 0.0
			}
		},	
		{
			"total_areas": 4,
			"randomize": false,
			"areas": [
			"firewallsSimple3",
			"firewallsSimple3b",
			"firewallsSimple3",
			"firewallsSimple3b"
			],
			"cameraOrientation": {
				"x": 0.0,
				"y": -5.0,
				"z": -2.0
			}
		},			
		{
			"total_areas": 3,
			"randomize": true,
			"areas": [
			"firewallsSimple",
			"firewallsSimple2"
			],
			"cameraOrientation": {
				"x": 0.0,
				"y": -3.0,
				"z": -2.0
			}
		},
		{
			"total_areas": 1,
			"randomize": true,
			"areas": [
			"container_descanso_cruz"
			],
			"cameraOrientation": {
				"x": 0.0,
				"y": 0.0,
				"z": 0.0
			}
		},		
		{
			"total_areas": 1,
			"randomize": true,
			"areas": ["escupe_frontal1 (1)",
			"escupe_frontal1 (1) 1",
			"escupe_frontal1 (1) 2",
			"escupe_frontal1 1",
			"escupe_frontal1 (2)",
			"escupe_frontal1",
			"escupe_frontal_fila",
			"escupe_frontal_fila 1"],
			"cameraOrientation": {
				"x": 0.0,
				"y": -4.0,
				"z": -2.0
			}
		},
		{
			"total_areas": 1,
			"randomize": true,
			"areas": ["navesSimple2"],
			"cameraOrientation": {
				"x": 0.0,
				"y": 0.0,
				"z": 0.0
			}
		},
		{
			"total_areas": 4,
			"randomize": false,
			"areas": ["firewallsBoss",
			"firewallsBossFree"],
			"cameraOrientation": {
				"x": 0.0,
				"y": -2.0,
				"z": -1.0
			}
		},
		{
			"total_areas": 2,
			"randomize": true,
			"areas": [
			"firewallsBossFree",
			"firewallsBossFree2"
			],
			"cameraOrientation": {
				"x": 0.0,
				"y": -4.0,
				"z": -2.0
			}
		}				
		
		],
		"backgroundSides": []
	}]
}